backup2swift/__init__.py
backup2swift/utils.py
backup2swift/backup.py
backup2swift/command.py
backup2swift/config.py
backup2swift/tests/__init__.py
backup2swift/tests/test__init__.py
backup2swift/tests/test_config.py
backup2swift/tests/test_command.py
backup2swift/tests/test_utils.py
backup2swift/tests/test_vars.py
backup2swift/tests/test_backup.py
backup2swift-0.9.2.dist-info/metadata.json
backup2swift-0.9.2.dist-info/WHEEL
backup2swift-0.9.2.dist-info/RECORD
backup2swift-0.9.2.dist-info/DESCRIPTION.rst
backup2swift-0.9.2.dist-info/METADATA
backup2swift-0.9.2.dist-info/entry_points.txt
backup2swift-0.9.2.dist-info/top_level.txt
backup2swift-0.9.2.data/data/share/backup2swift/examples/bu2sw.conf
backup2swift-0.9.2.data/data/share/backup2swift/examples/bu2sw_ignore_verify.conf
